Metadata-Version: 2.1
Name: imagefeatures
Version: 0.0.1
Summary: A library for processing image features in a dataframe.
Home-page: https://github.com/8W9aG/image-features
Author: Will Sackfield
Author-email: will.sackfield@gmail.com
License: MIT
Keywords: features,image
Classifier: License :: OSI Approved :: MIT License
Classifier: Programming Language :: Python :: 3
License-File: LICENSE
Requires-Dist: pandas>=2.2.3
Requires-Dist: pyarrow>=19.0.1
Requires-Dist: imgbeddings>=0.1.0
Requires-Dist: pillow>=11.2.1
Requires-Dist: requests>=2.32.3
Requires-Dist: numpy>=1.26.4
Requires-Dist: torch>=2.7.0
Requires-Dist: huggingface_hub<0.26.0
